cloudmesh_admin-4.3.10-py3.8-nspkg.pth
cloudmesh/admin/__init__.py
cloudmesh/admin/__version__.py
cloudmesh/admin/command/__init__.py
cloudmesh/admin/command/admin.py
cloudmesh/check/__init__.py
cloudmesh/check/command/__init__.py
cloudmesh/check/command/check.py
cloudmesh/management/__init__.py
cloudmesh/management/script.py
cloudmesh/management/configuration/SSHkey.py
cloudmesh/management/configuration/__init__.py
cloudmesh/management/configuration/arguments.py
cloudmesh/management/configuration/counter.py
cloudmesh/management/configuration/generic_config.py
cloudmesh/management/configuration/name.py
cloudmesh/management/configuration/operatingsystem.py
cloudmesh/mongo/CmDatabase.py
cloudmesh/mongo/DataBaseDecorator.py
cloudmesh/mongo/MongoDBController-new.py
cloudmesh/mongo/MongoDBController.py
cloudmesh/mongo/MongoDocker.py
cloudmesh/mongo/WindowsService.py
cloudmesh/mongo/__init__.py
cloudmesh/provider/__init__.py
cloudmesh/provider/command/__init__.py
cloudmesh/provider/command/provider.py
cloudmesh/source/Source.py
cloudmesh/source/__init__.py
cloudmesh/source/command/__init__.py
cloudmesh/source/command/source.py
cloudmesh/start/__init__.py
cloudmesh/start/command/__init__.py
cloudmesh/start/command/start.py
cloudmesh/stop/__init__.py
cloudmesh/stop/command/__init__.py
cloudmesh/stop/command/stop.py
cloudmesh_admin-4.3.10.dist-info/LICENSE
cloudmesh_admin-4.3.10.dist-info/METADATA
cloudmesh_admin-4.3.10.dist-info/WHEEL
cloudmesh_admin-4.3.10.dist-info/namespace_packages.txt
cloudmesh_admin-4.3.10.dist-info/top_level.txt
cloudmesh_admin-4.3.10.dist-info/RECORD
