Metadata-Version: 2.1
Name: cloudmesh-admin
Version: 4.3.10
Summary: A command called admin and foo for the cloudmesh shell
Home-page: https://github.com/cloudmesh/cloudmesh-admin
Author: Gregor von Laszewski
Author-email: laszewski@gmail.com
License: Apache 2.0
Platform: UNKNOWN
Classifier: Development Status :: 5 - Production/Stable
Classifier: Environment :: Web Environment
Classifier: Intended Audience :: Developers
Classifier: License :: OSI Approved :: BSD License
Classifier: Operating System :: OS Independent
Classifier: Programming Language :: Python
Classifier: Programming Language :: Python :: 2
Classifier: Programming Language :: Python :: 3
Requires-Dist: cloudmesh-configuration
Requires-Dist: cloudmesh-cmd5
Requires-Dist: cloudmesh-sys
Requires-Dist: cloudmesh-inventory
Requires-Dist: cloudmesh-abstract
Requires-Dist: pymongo
Requires-Dist: progress
